MANIFEST.in
Products.PlonePopoll-configure.zcml
README.txt
setup.cfg
setup.py
Products/__init__.py
Products.PlonePopoll.egg-info/PKG-INFO
Products.PlonePopoll.egg-info/SOURCES.txt
Products.PlonePopoll.egg-info/dependency_links.txt
Products.PlonePopoll.egg-info/entry_points.txt
Products.PlonePopoll.egg-info/namespace_packages.txt
Products.PlonePopoll.egg-info/not-zip-safe
Products.PlonePopoll.egg-info/requires.txt
Products.PlonePopoll.egg-info/top_level.txt
Products/PlonePopoll/ABOUT
Products/PlonePopoll/CHANGES
Products/PlonePopoll/LICENSE
Products/PlonePopoll/PlonePopollBackend.py
Products/PlonePopoll/PlonePopollTool.py
Products/PlonePopoll/README.txt
Products/PlonePopoll/TESTED_WITH
Products/PlonePopoll/__init__.py
Products/PlonePopoll/config.py
Products/PlonePopoll/configure.zcml
Products/PlonePopoll/interfaces.py
Products/PlonePopoll/product.txt
Products/PlonePopoll/refresh.txt
Products/PlonePopoll/tool.gif
Products/PlonePopoll/version.txt
Products/PlonePopoll/Extensions/Install.py
Products/PlonePopoll/Extensions/Migration.py
Products/PlonePopoll/Extensions/__init__.py
Products/PlonePopoll/browser/__init__.py
Products/PlonePopoll/browser/popoll.pt
Products/PlonePopoll/browser/popoll.py
Products/PlonePopoll/content/PlonePopoll.py
Products/PlonePopoll/content/__init__.py
Products/PlonePopoll/content/schemata.py
Products/PlonePopoll/doc/FAQ
Products/PlonePopoll/doc/PlonePopoll2.png
Products/PlonePopoll/doc/SCREENSHOTS
Products/PlonePopoll/doc/edit_form.png
Products/PlonePopoll/doc/edit_form2.png
Products/PlonePopoll/doc/icon.png
Products/PlonePopoll/doc/poll_result.png
Products/PlonePopoll/doc/poll_result2.png
Products/PlonePopoll/doc/poll_slot2.png
Products/PlonePopoll/doc/poll_view.png
Products/PlonePopoll/i18n/PlonePopoll.pot
Products/PlonePopoll/i18n/PlonePopoll_bg.po
Products/PlonePopoll/i18n/PlonePopoll_ca.po
Products/PlonePopoll/i18n/PlonePopoll_cs.po
Products/PlonePopoll/i18n/PlonePopoll_da.po
Products/PlonePopoll/i18n/PlonePopoll_de.po
Products/PlonePopoll/i18n/PlonePopoll_el.po
Products/PlonePopoll/i18n/PlonePopoll_en.po
Products/PlonePopoll/i18n/PlonePopoll_eo.po
Products/PlonePopoll/i18n/PlonePopoll_es.po
Products/PlonePopoll/i18n/PlonePopoll_eu.po
Products/PlonePopoll/i18n/PlonePopoll_fr.po
Products/PlonePopoll/i18n/PlonePopoll_it.po
Products/PlonePopoll/i18n/PlonePopoll_nl.po
