Metadata-Version: 1.0
Name: Products.PlonePopoll
Version: 2.7.0-beta2
Summary: A Poll tool for Plone 3.x
Home-page: http://ingeniweb.com
Author: Ingeniweb
Author-email: support@ingeniweb.com
License: GPL
Keywords: Zope Plone Poll
Platform: UNKNOWN
Classifier: Framework :: Plone
Classifier: Programming Language :: Python
Classifier: Topic :: Software Development :: Libraries :: Python Modules
